songkick/__init__.py
songkick/models.py
songkick/queries.py
songkick-0.2.2.dist-info/WHEEL
songkick-0.2.2.dist-info/METADATA
songkick-0.2.2.dist-info/RECORD
