Metadata-Version: 2.1
Name: songkick
Version: 0.2.2
Summary: A Python SDK for the Songkick API.
Author: Craig Anderson
Author-email: craiga@craiga.id.au
Requires-Python: >=3.6,<4.0
Classifier: Programming Language :: Python :: 3
Classifier: Programming Language :: Python :: 3.6
Classifier: Programming Language :: Python :: 3.7
Requires-Dist: python-dateutil (>=2.8,<3.0)
Requires-Dist: requests (>=2,<3)
